sldtk/__init__.py
sldtk/correction.py
sldtk/detection.py
sldtk/helpers.py
sldtk/plotting.py
sldtk/profile.py
sldtk/sldtk.py
sldtk/models/__init__.py
sldtk/models/limb_model.py
sldtk/models/linear.py
sldtk/models/polynomial.py
sldtk-0.1.0.dist-info/DESCRIPTION.rst
sldtk-0.1.0.dist-info/METADATA
sldtk-0.1.0.dist-info/RECORD
sldtk-0.1.0.dist-info/WHEEL
sldtk-0.1.0.dist-info/entry_points.txt
sldtk-0.1.0.dist-info/metadata.json
sldtk-0.1.0.dist-info/top_level.txt
