Metadata-Version: 2.0
Name: sldtk
Version: 0.1.0
Summary: The Solar Limb Darkening Toolkit
Home-page: https://github.com/Legendin/SLDTk
Author: Ariel Ladegaard
Author-email: legendin@gmail.com
License: MIT
Keywords: sun solar limb darkening toolkit correction image processing analysis modelling
Platform: UNKNOWN
Classifier: Development Status :: 3 - Alpha
Classifier: Environment :: Console
Classifier: Intended Audience :: Science/Research
Classifier: License :: OSI Approved :: MIT License
Classifier: Natural Language :: English
Classifier: Operating System :: POSIX :: Linux
Classifier: Programming Language :: Python :: 3 :: Only
Classifier: Topic :: Scientific/Engineering :: Astronomy
Classifier: Topic :: Scientific/Engineering :: Physics
Requires-Python: >=3
Requires-Dist: numpy (>=1)
Requires-Dist: opencv-python (>=3)
Requires-Dist: matplotlib (>=2)
